cast_convert/__init__.py
cast_convert/__main__.py
cast_convert/py.typed
cast_convert/assets/devices.yml
cast_convert/assets/support.yml
cast_convert/assets/test-devices.yml
cast_convert/cli/__init__.py
cast_convert/cli/commands.py
cast_convert/cli/helpers.py
cast_convert/core/__init__.py
cast_convert/core/base.py
cast_convert/core/exceptions.py
cast_convert/core/fmt.py
cast_convert/core/parse.py
cast_convert/core/rules.py
cast_convert/core/convert/__init__.py
cast_convert/core/convert/run.py
cast_convert/core/convert/transcode.py
cast_convert/core/convert/watch.py
cast_convert/core/media/__init__.py
cast_convert/core/media/base.py
cast_convert/core/media/codecs.py
cast_convert/core/media/formats.py
cast_convert/core/media/profiles.py
cast_convert/core/model/__init__.py
cast_convert/core/model/device.py
cast_convert/core/model/video.py
cast_convert-0.13.1.dist-info/LICENSE
cast_convert-0.13.1.dist-info/METADATA
cast_convert-0.13.1.dist-info/WHEEL
cast_convert-0.13.1.dist-info/entry_points.txt
cast_convert-0.13.1.dist-info/top_level.txt
cast_convert-0.13.1.dist-info/zip-safe
cast_convert-0.13.1.dist-info/RECORD
